README.md
setup.py
tap_campaign_monitor/__init__.py
tap_campaign_monitor/client.py
tap_campaign_monitor/config.py
tap_campaign_monitor/state.py
tap_campaign_monitor/timezones.py
tap_campaign_monitor.egg-info/PKG-INFO
tap_campaign_monitor.egg-info/SOURCES.txt
tap_campaign_monitor.egg-info/dependency_links.txt
tap_campaign_monitor.egg-info/entry_points.txt
tap_campaign_monitor.egg-info/requires.txt
tap_campaign_monitor.egg-info/top_level.txt
tap_campaign_monitor/schemas/campaign_bounces.json
tap_campaign_monitor/schemas/campaign_clicks.json
tap_campaign_monitor/schemas/campaign_email_client_usage.json
tap_campaign_monitor/schemas/campaign_opens.json
tap_campaign_monitor/schemas/campaign_recipients.json
tap_campaign_monitor/schemas/campaign_spam_complaints.json
tap_campaign_monitor/schemas/campaign_summary.json
tap_campaign_monitor/schemas/campaign_unsubscribes.json
tap_campaign_monitor/schemas/campaigns.json
tap_campaign_monitor/schemas/list_active_subscribers.json
tap_campaign_monitor/schemas/list_bounced_subscribers.json
tap_campaign_monitor/schemas/list_deleted_subscribers.json
tap_campaign_monitor/schemas/list_details.json
tap_campaign_monitor/schemas/list_unconfirmed_subscribers.json
tap_campaign_monitor/schemas/list_unsubscribed_subscribers.json
tap_campaign_monitor/schemas/lists.json
tap_campaign_monitor/streams/__init__.py
tap_campaign_monitor/streams/base.py
tap_campaign_monitor/streams/campaign_bounces.py
tap_campaign_monitor/streams/campaign_clicks.py
tap_campaign_monitor/streams/campaign_email_client_usage.py
tap_campaign_monitor/streams/campaign_opens.py
tap_campaign_monitor/streams/campaign_recipients.py
tap_campaign_monitor/streams/campaign_spam_complaints.py
tap_campaign_monitor/streams/campaign_summary.py
tap_campaign_monitor/streams/campaign_unsubscribes.py
tap_campaign_monitor/streams/campaigns.py
tap_campaign_monitor/streams/list_active_subscribers.py
tap_campaign_monitor/streams/list_bounced_subscribers.py
tap_campaign_monitor/streams/list_deleted_subscribers.py
tap_campaign_monitor/streams/list_details.py
tap_campaign_monitor/streams/list_unconfirmed_subscribers.py
tap_campaign_monitor/streams/list_unsubscribed_subscribers.py
tap_campaign_monitor/streams/lists.py